plotease/__init__.py
plotease/eda/__init__.py
plotease/eda/distribution.py
plotease-0.1.0.dist-info/licenses/LICENSE
plotease-0.1.0.dist-info/METADATA
plotease-0.1.0.dist-info/WHEEL
plotease-0.1.0.dist-info/top_level.txt
plotease-0.1.0.dist-info/RECORD
