Metadata-Version: 2.4
Name: plotease
Version: 0.1.0
Summary: High-level plotting library for EDA and model evaluation
Author: Rayyan Ahmed, Irtat Mobin, Agha Haris
License: MIT License
Keywords: eda,visualization,machine-learning,matplotlib,seaborn
Classifier: Programming Language :: Python :: 3
Classifier: License :: OSI Approved :: MIT License
Classifier: Operating System :: OS Independent
Classifier: Topic :: Scientific/Engineering :: Visualization
Classifier: Intended Audience :: Science/Research
Classifier: Development Status :: 3 - Alpha
Requires-Python: >=3.8
License-File: LICENSE
Requires-Dist: matplotlib
Requires-Dist: seaborn
Requires-Dist: pandas
Requires-Dist: numpy
Dynamic: license-file
